mei2volpiano/__init__.py
mei2volpiano/driver.py
mei2volpiano/mei2volpiano.py
mei2volpiano-0.8.2.dist-info/entry_points.txt
mei2volpiano-0.8.2.dist-info/LICENSE
mei2volpiano-0.8.2.dist-info/WHEEL
mei2volpiano-0.8.2.dist-info/METADATA
mei2volpiano-0.8.2.dist-info/RECORD
