Metadata-Version: 2.1
Name: mei2volpiano
Version: 0.8.2
Summary: 
Home-page: https://github.com/DDMAL/MEI2Volpiano
Author: DDMAL
Requires-Python: >=3.6,<4.0
Classifier: Programming Language :: Python :: 3
Classifier: Programming Language :: Python :: 3.6
Classifier: Programming Language :: Python :: 3.7
Classifier: Programming Language :: Python :: 3.8
Classifier: Programming Language :: Python :: 3.9
Provides-Extra: docs
Requires-Dist: pytz (>=2021.1,<2022.0)
Project-URL: Repository, https://github.com/DDMAL/MEI2Volpiano
